aina/__init__.py
aina/aina.py
aina/render.py
aina-0.1.3.dist-info/AUTHORS.rst
aina-0.1.3.dist-info/LICENSE
aina-0.1.3.dist-info/METADATA
aina-0.1.3.dist-info/WHEEL
aina-0.1.3.dist-info/entry_points.txt
aina-0.1.3.dist-info/top_level.txt
aina-0.1.3.dist-info/RECORD
