Metadata-Version: 2.1
Name: aina
Version: 0.1.3
Summary: Let the logs flow
Home-page: https://github.com/ilovetux/aina
Author: iLoveTux
Author-email: cliffbressette@gmail.com
License: GNU General Public License v3
Keywords: aina
Platform: UNKNOWN
Classifier: Development Status :: 2 - Pre-Alpha
Classifier: Intended Audience :: Developers
Classifier: License :: OSI Approved :: GNU General Public License v3 (GPLv3)
Classifier: Natural Language :: English
Classifier: Programming Language :: Python :: 3.5
Classifier: Programming Language :: Python :: 3.6
Classifier: Programming Language :: Python :: 3.7
Requires-Dist: Click (>=6.0)
